{
  "case_number": "51-2020-TR-00624",
  "document_link_count": 0,
  "document_links": [],
  "has_document_links": false,
  "has_register_of_actions": true,
  "indexed_entries": [
    {
      "date": "12/31/2025",
      "description": "Auto-generated event - DOT Integration",
      "index_number": "1",
      "title": "Citation"
    },
    {
      "date": "04/23/2020",
      "description": "Second or Subsequent Driving w/o Liability",
      "index_number": "2",
      "title": "Order"
    },
    {
      "date": "05/08/2020",
      "description": "To States Attorney - No Liability Insurance",
      "index_number": "3",
      "title": "Notice"
    }
  ],
  "indexed_entry_count": 3
}
