{
  "case_number": "23-2019-SC-00020",
  "document_link_count": 0,
  "document_links": [],
  "has_document_links": false,
  "has_register_of_actions": true,
  "indexed_entries": [
    {
      "date": "07/15/2019",
      "description": "Robert Cofell Unpaid propane deliver from Jan. 2019 Delivery made to Marion address",
      "index_number": "1",
      "title": "Claim Affidavit"
    },
    {
      "date": "07/15/2019",
      "description": "Robert Cofell Affidavit of Identification 914 11th Ave NE Apt. 8 Jamestown, ND 58401",
      "index_number": "2",
      "title": "Affidavit"
    },
    {
      "date": "08/13/2019",
      "description": "Letter to dismiss case. Defendant was unable to be served.",
      "index_number": "3",
      "title": "Letter"
    },
    {
      "date": "09/03/2019",
      "description": "of Dismissal",
      "index_number": "4",
      "title": "Proposed Judgment"
    },
    {
      "date": "09/03/2019",
      "description": "of Dismissal",
      "index_number": "5",
      "title": "Judgment"
    }
  ],
  "indexed_entry_count": 5
}
