{
  "case_number": "51-2020-CR-00159",
  "document_link_count": 0,
  "document_links": [],
  "has_document_links": false,
  "has_register_of_actions": true,
  "indexed_entries": [
    {
      "date": "04/21/2020",
      "description": "51smrC100200203",
      "index_number": "1",
      "title": "Citation"
    },
    {
      "date": "02/03/2020",
      "description": "Misdemeanor",
      "index_number": "4",
      "title": "Scheduling Order"
    },
    {
      "date": "02/03/2020",
      "description": "Bail",
      "index_number": "5",
      "title": "Order"
    },
    {
      "date": "02/03/2020",
      "description": "from North Dakota Department of Transportation - Driver's License Division",
      "index_number": "6",
      "title": "Notification of Rights and Acknowledgement"
    },
    {
      "date": "04/15/2020",
      "description": "Affidavit of Service-Perry",
      "index_number": "8",
      "title": "Service Document"
    },
    {
      "date": "04/16/2020",
      "description": "to Dismiss",
      "index_number": "9",
      "title": "Motion"
    },
    {
      "date": "04/16/2020",
      "description": "Order of Dismissal",
      "index_number": "10",
      "title": "Proposed Order"
    },
    {
      "date": "04/21/2020",
      "description": "of Dismissal (Copy to Defendant)",
      "index_number": "11",
      "title": "Order"
    }
  ],
  "indexed_entry_count": 8
}
