{
  "case_number": "08-2019-CR-03073",
  "document_link_count": 0,
  "document_links": [],
  "has_document_links": false,
  "has_register_of_actions": true,
  "indexed_entries": [
    {
      "date": "06/08/2020",
      "description": "Criminal Summons - Served",
      "index_number": "1",
      "title": "Information"
    },
    {
      "date": "10/29/2019",
      "description": "Criminal Summons - Served",
      "index_number": "5",
      "title": "Sheriff's Return Served"
    },
    {
      "date": "11/20/2019",
      "description": "Order - promise to appear, atty app, drug patch, contact PO, remain in ND",
      "index_number": "6",
      "title": "Notification of Rights and Acknowledgement"
    },
    {
      "date": "11/29/2019",
      "description": "- Prelim/Arraignment",
      "index_number": "8",
      "title": "Notice of Hearing"
    },
    {
      "date": "12/09/2019",
      "description": "- prelim notice",
      "index_number": "9",
      "title": "Returned Mail"
    },
    {
      "date": "12/23/2019",
      "description": "Approved",
      "index_number": "10",
      "title": "Bench Warrant Issued"
    },
    {
      "date": "01/21/2020",
      "description": "Bench Warrant - Served",
      "index_number": "12",
      "title": "Notice of Eligibility for Appointed Counsel"
    },
    {
      "date": "01/21/2020",
      "description": "Assignment of Counsel-Matt Arthurs",
      "index_number": "14",
      "title": "Bench Warrant Served"
    },
    {
      "date": "01/22/2020",
      "description": "Amended Order - $1000 unsecured; contact atty weekly; contact PO; drug patch",
      "index_number": "16",
      "title": "Notice to Defendant and Consent to Reliable Electronic Means"
    },
    {
      "date": "01/24/2020",
      "description": "- Prelim/Arraignment",
      "index_number": "19",
      "title": "Notice of Hearing"
    },
    {
      "date": "01/31/2020",
      "description": "Request to Revoke Bail, Forfeit Bond, and Issue Bench Warrant",
      "index_number": "20",
      "title": "Request"
    },
    {
      "date": "01/31/2020",
      "description": "Exhibit 1-Program Violation",
      "index_number": "21",
      "title": "Exhibit"
    },
    {
      "date": "01/31/2020",
      "description": "Proposed Order to Request to Revoke Bond, Forfeit Bail and Issue Bench Warrant- State",
      "index_number": "22",
      "title": "Proposed Order"
    },
    {
      "date": "01/31/2020",
      "description": "Bench Warrant- State",
      "index_number": "23",
      "title": "Proposed Order"
    },
    {
      "date": "01/31/2020",
      "description": "Matthew Arthurs",
      "index_number": "24",
      "title": "Service Document"
    },
    {
      "date": "02/04/2020",
      "description": "to Revoke Bond and Issue Bench Warrant",
      "index_number": "25",
      "title": "Order"
    },
    {
      "date": "02/04/2020",
      "description": "Bench Warrant - Served",
      "index_number": "26",
      "title": "Bench Warrant Issued"
    },
    {
      "date": "02/13/2020",
      "description": "Second Amended Bond (250 cash, remain in ND, Drug patch put on before release)",
      "index_number": "28",
      "title": "Bench Warrant Served"
    },
    {
      "date": "02/18/2020",
      "description": "to Bond Remiter: Eric McKenzie",
      "index_number": "32",
      "title": "Bench Warrant Issued"
    },
    {
      "date": "04/15/2020",
      "description": "Bench Warrant - Served",
      "index_number": "34",
      "title": "Sheriff's Return Served"
    },
    {
      "date": "04/15/2020",
      "description": "3rd Amended Order - $250 cash, previous $250 applies, contact PO, sign release for Ideal Options to the court, remain in Burleigh/Morton",
      "index_number": "35",
      "title": "Bench Warrant Served"
    },
    {
      "date": "04/17/2020",
      "description": "- Prelim/Arraignment",
      "index_number": "39",
      "title": "Notice of Hearing"
    },
    {
      "date": "04/17/2020",
      "description": "- Amended Prelim (judge change)",
      "index_number": "40",
      "title": "Notice of Scheduling Change"
    },
    {
      "date": "04/27/2020",
      "description": "from Ideal Options",
      "index_number": "41",
      "title": "Report"
    },
    {
      "date": "05/04/2020",
      "description": "Report from Ideal Options",
      "index_number": "42",
      "title": "Report"
    },
    {
      "date": "06/08/2020",
      "description": "Via Zoom meeting ID 850 1519 9559 or 1-669-900-9128 OR 1-646-558-8656",
      "index_number": "43",
      "title": "Appendix A"
    },
    {
      "date": "04/23/2021",
      "description": "Petition for Revocation of Probation",
      "index_number": "46",
      "title": "Petition for Revocation"
    },
    {
      "date": "04/23/2021",
      "description": "Order to Apprehend - ASA Dennis Ingold (In Custody)",
      "index_number": "47",
      "title": "Proposed Order"
    },
    {
      "date": "04/23/2021",
      "description": "(In custody)",
      "index_number": "48",
      "title": "Order to Apprehend Warrant Issued"
    },
    {
      "date": "04/23/2021",
      "description": "Covers 08-2019-CR-3073 and 08-2021-CR-1279",
      "index_number": "50",
      "title": "Notification of Rights and Acknowledgement"
    },
    {
      "date": "04/23/2021",
      "description": "Motion to Modify Bond",
      "index_number": "52",
      "title": "Notice to Defendant and Consent to Reliable Electronic Means"
    },
    {
      "date": "04/26/2021",
      "description": "Order to Modify Bond - ASA Dennis Ingold",
      "index_number": "54",
      "title": "Proposed Order"
    },
    {
      "date": "04/26/2021",
      "description": "Unsworn Declaration of Service by Mail Pamela Yellow Earrings",
      "index_number": "55",
      "title": "Service of Motion"
    },
    {
      "date": "04/26/2021",
      "description": "Amended - Covers 08-2019-CR-3073 and 08-2021-CR-1279",
      "index_number": "56",
      "title": "Bond"
    },
    {
      "date": "05/04/2021",
      "description": "- Remote Hearing - Revocation - ZOOM",
      "index_number": "57",
      "title": "Notice of Hearing"
    },
    {
      "date": "06/14/2021",
      "description": "Request to Revoke Bond, Forfeit Bail, and Issue Bench Warrant",
      "index_number": "59",
      "title": "Request"
    },
    {
      "date": "06/14/2021",
      "description": "State's Exhibit #1 - PRE-Trial 24/7 Program Violation",
      "index_number": "60",
      "title": "Exhibit"
    },
    {
      "date": "06/14/2021",
      "description": "Order - State of North Dakota",
      "index_number": "61",
      "title": "Proposed Order"
    },
    {
      "date": "06/14/2021",
      "description": "Bench Warrant - State of North Dakota",
      "index_number": "62",
      "title": "Proposed Order"
    },
    {
      "date": "06/14/2021",
      "description": "Unsworn Declaration of Service by Mail Pro Se Pamela YellowEarrings",
      "index_number": "63",
      "title": "Service Document"
    },
    {
      "date": "06/16/2021",
      "description": "Approved",
      "index_number": "64",
      "title": "Application for Indigent Defense Services"
    },
    {
      "date": "06/16/2021",
      "description": "Assignment of Counsel-James Wiese",
      "index_number": "65",
      "title": "Notice of Eligibility for Appointed Counsel"
    },
    {
      "date": "06/16/2021",
      "description": "to Revoke Bond, Forfeit Bail, and Issue Bench Warrant",
      "index_number": "67",
      "title": "Order"
    },
    {
      "date": "06/16/2021",
      "description": "Demand for Discovery - James Wiese",
      "index_number": "68",
      "title": "Bench Warrant Issued"
    },
    {
      "date": "06/21/2021",
      "description": "Certificate of Service - State's Attorney",
      "index_number": "70",
      "title": "Service Document"
    },
    {
      "date": "06/22/2021",
      "description": "Response to and Request for Discovery and Notice of Intent to Use Evidence",
      "index_number": "71",
      "title": "Response"
    },
    {
      "date": "06/22/2021",
      "description": "Unsworn Declaration of Service by Electronic Filing Attorney James Wiese",
      "index_number": "72",
      "title": "Service Document"
    },
    {
      "date": "07/07/2021",
      "description": "FTA;Via Zoom meeting ID 827 7032 0121 or call 1-669-900-9128",
      "index_number": "73",
      "title": "Bench Warrant Issued"
    },
    {
      "date": "08/30/2021",
      "description": "Bench Warrant-Served",
      "index_number": "74",
      "title": "Sheriff's Return Served"
    },
    {
      "date": "08/30/2021",
      "description": "Bench Warrant - Served",
      "index_number": "75",
      "title": "Sheriff's Return Served"
    },
    {
      "date": "08/30/2021",
      "description": "Remote Hearing - Revocation of Probation",
      "index_number": "76",
      "title": "Bench Warrant Served"
    },
    {
      "date": "08/31/2021",
      "description": "via ZOOM - meeting ID 876 5055 3850 - zoom.com or call 669-900-9128",
      "index_number": "80",
      "title": "Notice to Defendant and Consent to Reliable Electronic Means"
    },
    {
      "date": "09/14/2021",
      "description": "Amended Criminal Judgment",
      "index_number": "81",
      "title": "Proposed Judgment"
    },
    {
      "date": "09/15/2021",
      "description": "Amended",
      "index_number": "82",
      "title": "Criminal Judgment"
    }
  ],
  "indexed_entry_count": 54
}
