{
  "case_number": "08-2019-SC-00223",
  "document_link_count": 0,
  "document_links": [],
  "has_document_links": false,
  "has_register_of_actions": true,
  "indexed_entries": [
    {
      "date": "07/09/2019",
      "description": "Filed by Pulkrabek Law Office",
      "index_number": "1",
      "title": "Claim Affidavit"
    },
    {
      "date": "07/09/2019",
      "description": "Affidavit of Identification, Filed by Pulkrabek Law Office",
      "index_number": "2",
      "title": "Affidavit"
    },
    {
      "date": "07/09/2019",
      "description": "Exhibit 1, Complaint, Filed by Pulkrabek Law Office",
      "index_number": "3",
      "title": "Exhibit"
    },
    {
      "date": "07/09/2019",
      "description": "Exhibit 2, Bill, Filed by Pulkrabek Law Office",
      "index_number": "4",
      "title": "Exhibit"
    },
    {
      "date": "07/15/2019",
      "description": "Service to Ryan Dietz, Filed by Pulkrabek Law Office",
      "index_number": "5",
      "title": "Small Claims Served"
    },
    {
      "date": "08/02/2019",
      "description": "Satisfaction of Judgment, Filed by Pulkrabek Law Office",
      "index_number": "6",
      "title": "Judgment"
    }
  ],
  "indexed_entry_count": 6
}
