{
  "case_number": "02-2019-CV-00085",
  "document_link_count": 0,
  "document_links": [],
  "has_document_links": false,
  "has_register_of_actions": true,
  "indexed_entries": [
    {
      "date": "04/25/2019",
      "description": "Complaint",
      "index_number": "1",
      "title": "Complaint"
    },
    {
      "date": "04/25/2019",
      "description": "Summons",
      "index_number": "2",
      "title": "Summons"
    },
    {
      "date": "04/25/2019",
      "description": "Sheriff's Return:Personally served Robert Lawrence Schwartz",
      "index_number": "3",
      "title": "Service Document"
    },
    {
      "date": "04/25/2019",
      "description": "Affidavit of Default and No Answer",
      "index_number": "4",
      "title": "Affidavit"
    },
    {
      "date": "04/25/2019",
      "description": "Affidavit of Proof",
      "index_number": "5",
      "title": "Affidavit"
    },
    {
      "date": "04/25/2019",
      "description": "Affidavit of Identification and Non-Military Service",
      "index_number": "6",
      "title": "Affidavit"
    },
    {
      "date": "04/25/2019",
      "description": "Proposed Statement of Costs and Disbursements-Proposed and Filed by Daniel H. Oster",
      "index_number": "7",
      "title": "Proposed Statement of Costs and Disbursements"
    },
    {
      "date": "04/25/2019",
      "description": "Proposed Order for Judgment - Proposed and Filed by Daniel H. Oster",
      "index_number": "8",
      "title": "Proposed Order"
    },
    {
      "date": "04/25/2019",
      "description": "Proposed Judgment on Default - Proposed and Filed by Daniel H Oster",
      "index_number": "9",
      "title": "Proposed Judgment"
    },
    {
      "date": "04/25/2019",
      "description": "Exhibit A - Assignment",
      "index_number": "10",
      "title": "Exhibit"
    },
    {
      "date": "04/25/2019",
      "description": "Sheriff's Return: Personally Served Sandra Schwartz",
      "index_number": "11",
      "title": "Service Document"
    },
    {
      "date": "04/26/2019",
      "description": "Entry of Judgment",
      "index_number": "12",
      "title": "Statement of Costs and Disbursements"
    },
    {
      "date": "05/09/2019",
      "description": "Affidavit of Service by Mail - Robert Lawrence Schwartz and Sandy Schwartz",
      "index_number": "16",
      "title": "Service Document"
    },
    {
      "date": "01/10/2020",
      "description": "Motion of Intent to Take Default Judgment Against Garnishee",
      "index_number": "17",
      "title": "Motion"
    },
    {
      "date": "01/10/2020",
      "description": "Brief in Support of Motoin for Default Judgment Against Garnishee",
      "index_number": "18",
      "title": "Brief"
    },
    {
      "date": "01/10/2020",
      "description": "Affidavit of Daniel H Oster",
      "index_number": "19",
      "title": "Affidavit"
    },
    {
      "date": "01/10/2020",
      "description": "Exhibit A - Notice Prior to Garnishment",
      "index_number": "20",
      "title": "Exhibit"
    },
    {
      "date": "01/10/2020",
      "description": "Exhibit B - Service of Garnishment on Defendant",
      "index_number": "21",
      "title": "Exhibit"
    },
    {
      "date": "01/10/2020",
      "description": "Exhibit C - Service of Garnishment on Garnishee and Garnishee Summons",
      "index_number": "22",
      "title": "Exhibit"
    },
    {
      "date": "01/10/2020",
      "description": "Exhibit D - Notice to Garnishee to return Garnishment Disclosure",
      "index_number": "23",
      "title": "Exhibit"
    },
    {
      "date": "01/10/2020",
      "description": "Order for Default Judgment Against Garnishee - Proposed and filed by Daniel H Oster",
      "index_number": "24",
      "title": "Proposed Order"
    },
    {
      "date": "01/10/2020",
      "description": "Judgment - Proposed and filed by Daniel H Oster",
      "index_number": "25",
      "title": "Proposed Judgment"
    },
    {
      "date": "01/10/2020",
      "description": "Affidavit of Service by Mail -Robert Lawrence Schwartz and Schwartz Trucking",
      "index_number": "26",
      "title": "Service of Motion"
    },
    {
      "date": "02/03/2020",
      "description": "for Default Judgment Against Garnishee",
      "index_number": "27",
      "title": "Order"
    },
    {
      "date": "02/03/2020",
      "description": "Notice of Entry of Judgment",
      "index_number": "28",
      "title": "Judgment"
    },
    {
      "date": "04/09/2020",
      "description": "Affidavit of Service by Mail-Robert Lawrence Schwartz and Schwartz Trucking",
      "index_number": "30",
      "title": "Service Document"
    },
    {
      "date": "12/14/2023",
      "description": "Satisfaction of Judgment",
      "index_number": "31",
      "title": "Satisfaction of Judgment"
    }
  ],
  "indexed_entry_count": 27
}
