{
  "case_number": "05-2019-PR-00064",
  "document_link_count": 0,
  "document_links": [],
  "has_document_links": false,
  "has_register_of_actions": true,
  "indexed_entries": [
    {
      "date": "10/22/2019",
      "description": "Application",
      "index_number": "1",
      "title": "Application for Appointment of Personal Representative"
    },
    {
      "date": "10/22/2019",
      "description": "Letters of Administration",
      "index_number": "2",
      "title": "Proposed Letters"
    },
    {
      "date": "10/22/2019",
      "description": "Waiver and Consent to Appointment of Personal Representative",
      "index_number": "3",
      "title": "Waiver"
    },
    {
      "date": "10/22/2019",
      "description": "Statement of Appointment of Personal Representative",
      "index_number": "4",
      "title": "Proposed Order"
    },
    {
      "date": "10/22/2019",
      "description": "Affidavit of Forwarding Copy to Department of Human Services",
      "index_number": "5",
      "title": "Service Document"
    },
    {
      "date": "10/24/2019",
      "description": "Statement of Appointment of Personal Representative",
      "index_number": "6",
      "title": "Letters of Administration"
    }
  ],
  "indexed_entry_count": 6
}
