{
  "case_number": "18-2020-PR-00014",
  "document_link_count": 0,
  "document_links": [],
  "has_document_links": false,
  "has_register_of_actions": true,
  "indexed_entries": [
    {
      "date": "01/13/2020",
      "description": "Application for Informal Probate of Will and Appointment of a personal Representative",
      "index_number": "1",
      "title": "Application for Appointment of Personal Representative"
    },
    {
      "date": "01/13/2020",
      "description": "Letters Testamentary",
      "index_number": "2",
      "title": "Proposed Letters"
    },
    {
      "date": "01/13/2020",
      "description": "Statement of Informal Probate of Will and Appointment of a Personal Representative",
      "index_number": "3",
      "title": "Proposed Order"
    },
    {
      "date": "01/13/2020",
      "description": "Certificate of Death",
      "index_number": "4",
      "title": "Certificate"
    },
    {
      "date": "01/13/2020",
      "description": "Last Will and Testament",
      "index_number": "5",
      "title": "Last Will and Testament"
    },
    {
      "date": "01/13/2020",
      "description": "Letters Testamentary",
      "index_number": "6",
      "title": "Notice of Assignment and Case Number"
    },
    {
      "date": "01/23/2020",
      "description": "Statement of Informal Probate of Will and Appointment of a Personal Representative",
      "index_number": "8",
      "title": "Order"
    },
    {
      "date": "01/31/2020",
      "description": "Notice and Information to Heirs and Devisees",
      "index_number": "9",
      "title": "Notice"
    },
    {
      "date": "01/31/2020",
      "description": "Affidavit of Service by mail to heirs",
      "index_number": "10",
      "title": "Service Document"
    },
    {
      "date": "01/31/2020",
      "description": "Affidavit of Service by mail to ND Dept of Human Services",
      "index_number": "11",
      "title": "Service Document"
    },
    {
      "date": "02/07/2020",
      "description": "Affidavit of Service by mail (to Kristi)",
      "index_number": "12",
      "title": "Service Document"
    },
    {
      "date": "02/20/2020",
      "description": "Affidavit of Publication",
      "index_number": "13",
      "title": "Affidavit"
    },
    {
      "date": "10/23/2020",
      "description": "Notice of Proposed partial distribution",
      "index_number": "14",
      "title": "Notice"
    },
    {
      "date": "10/23/2020",
      "description": "Affidavit of Service by mail to heirs",
      "index_number": "15",
      "title": "Service Document"
    },
    {
      "date": "12/02/2020",
      "description": "Affidavit of Service by mail to heir",
      "index_number": "16",
      "title": "Service Document"
    },
    {
      "date": "11/03/2021",
      "description": "Concent (Dru)",
      "index_number": "17",
      "title": "Consent"
    },
    {
      "date": "11/03/2021",
      "description": "Consent (Russell)",
      "index_number": "18",
      "title": "Consent"
    },
    {
      "date": "11/03/2021",
      "description": "Consent (Carlene)",
      "index_number": "19",
      "title": "Consent"
    },
    {
      "date": "11/03/2021",
      "description": "Consent (Kristi)",
      "index_number": "20",
      "title": "Consent"
    },
    {
      "date": "11/03/2021",
      "description": "Consent (Heidi)",
      "index_number": "21",
      "title": "Consent"
    },
    {
      "date": "11/03/2021",
      "description": "Consent (Michael)",
      "index_number": "22",
      "title": "Consent"
    },
    {
      "date": "11/03/2021",
      "description": "COnsent (Gary)",
      "index_number": "23",
      "title": "Consent"
    },
    {
      "date": "11/03/2021",
      "description": "Consent (Victor)",
      "index_number": "24",
      "title": "Consent"
    },
    {
      "date": "11/03/2021",
      "description": "Consent (Deborah)",
      "index_number": "25",
      "title": "Consent"
    },
    {
      "date": "11/03/2021",
      "description": "Consent (Alithea)",
      "index_number": "26",
      "title": "Consent"
    },
    {
      "date": "11/08/2021",
      "description": "Notice of Proposed Final Distribution",
      "index_number": "27",
      "title": "Notice"
    },
    {
      "date": "11/08/2021",
      "description": "Affidavit of Service by mail",
      "index_number": "28",
      "title": "Service Document"
    },
    {
      "date": "12/16/2021",
      "description": "Inventory and appraisement",
      "index_number": "29",
      "title": "Inventory & Appraisement"
    },
    {
      "date": "12/16/2021",
      "description": "consent (Alithea)",
      "index_number": "30",
      "title": "Consent"
    },
    {
      "date": "12/16/2021",
      "description": "Consent (Kristi",
      "index_number": "31",
      "title": "Consent"
    },
    {
      "date": "12/16/2021",
      "description": "Consent (Michael",
      "index_number": "32",
      "title": "Consent"
    },
    {
      "date": "12/16/2021",
      "description": "Consent (Deborah",
      "index_number": "33",
      "title": "Consent"
    },
    {
      "date": "12/16/2021",
      "description": "Consent ( Heidi",
      "index_number": "34",
      "title": "Consent"
    },
    {
      "date": "12/16/2021",
      "description": "Consent ( Gary",
      "index_number": "35",
      "title": "Consent"
    },
    {
      "date": "12/16/2021",
      "description": "Consent ( Dru",
      "index_number": "36",
      "title": "Consent"
    },
    {
      "date": "12/16/2021",
      "description": "Consent ( Carlene",
      "index_number": "37",
      "title": "Consent"
    },
    {
      "date": "12/16/2021",
      "description": "Consent ( Victor",
      "index_number": "38",
      "title": "Consent"
    },
    {
      "date": "12/16/2021",
      "description": "Consent ( Russell",
      "index_number": "39",
      "title": "Consent"
    },
    {
      "date": "12/16/2021",
      "description": "Affidavit of Serivce by mail",
      "index_number": "40",
      "title": "Service Document"
    },
    {
      "date": "12/16/2021",
      "description": "Final Report and Accounting",
      "index_number": "41",
      "title": "Final Report and Accounting"
    },
    {
      "date": "12/16/2021",
      "description": "Personal Representatives sworn statement to close the estate",
      "index_number": "42",
      "title": "Personal Representative's Sworn Statement to Close Estate"
    }
  ],
  "indexed_entry_count": 41
}
